mipi_try_actions/__init__.py
mipi_try_actions/main.py
mipi_try_actions-0.1.2.dist-info/METADATA
mipi_try_actions-0.1.2.dist-info/WHEEL
mipi_try_actions-0.1.2.dist-info/RECORD
